artemis/__init__.py
artemis/main.py
artemis_lab-0.0.0.dist-info/METADATA
artemis_lab-0.0.0.dist-info/WHEEL
artemis_lab-0.0.0.dist-info/top_level.txt
artemis_lab-0.0.0.dist-info/RECORD
