Metadata-Version: 2.1
Name: artemis_lab
Version: 0.0.0
Summary: Artemis core can be defined as framework to create and play modular pipelines. Coming soon...
Author-email: artemis-cnes <artemis-cnes@cnes.fr>
Classifier: Programming Language :: Python
Classifier: Programming Language :: Python :: 3
Classifier: Programming Language :: Python :: 3.8
Classifier: Operating System :: OS Independent
Classifier: Intended Audience :: Science/Research
Classifier: Topic :: Scientific/Engineering
Classifier: Topic :: Scientific/Engineering :: Image Processing
Requires-Python: >=3.8
